README.txt
bootstrap.py
buildout.cfg
setup.cfg
setup.py
collective/__init__.py
collective.googleforms.egg-info/PKG-INFO
collective.googleforms.egg-info/SOURCES.txt
collective.googleforms.egg-info/dependency_links.txt
collective.googleforms.egg-info/entry_points.txt
collective.googleforms.egg-info/namespace_packages.txt
collective.googleforms.egg-info/not-zip-safe
collective.googleforms.egg-info/paster_plugins.txt
collective.googleforms.egg-info/requires.txt
collective.googleforms.egg-info/top_level.txt
collective/googleforms/__init__.py
collective/googleforms/configure.zcml
collective/googleforms/tests.py
collective/googleforms/browser/__init__.py
collective/googleforms/browser/configure.zcml
collective/googleforms/browser/googleformview.pt
collective/googleforms/browser/googleformview.py
collective/googleforms/interfaces/__init__.py
collective/googleforms/interfaces/browserlayer.py
collective/googleforms/locales/en/LC_MESSAGES/README.txt
collective/googleforms/locales/fr/LC_MESSAGES/README.txt
collective/googleforms/profiles/default/browserlayer.xml
collective/googleforms/profiles/default/metadata.xml
collective/googleforms/profiles/default/types/Link.xml
docs/HISTORY.txt
docs/INSTALL.txt
docs/LICENSE.GPL
docs/LICENSE.txt