Metadata-Version: 1.0
Name: collective.googleforms
Version: 1.0a1
Summary: Display google forms (spreadsheet) in Plone
Home-page: http://svn.plone.org/svn/collective/
Author: JeanMichel FRANCOIS aka toutpt
Author-email: toutpt@gmail.com
License: GPL
Platform: UNKNOWN
Classifier: Framework :: Plone
Classifier: Programming Language :: Python
